py_mirror_cli-0.1.0.dist-info/licenses/LICENSE
pyrm/__init__.py
pyrm/cli.py
pyrm/config.py
pyrm/editor.py
pyrm/registry.py
pyrm/utils.py
py_mirror_cli-0.1.0.dist-info/METADATA
py_mirror_cli-0.1.0.dist-info/WHEEL
py_mirror_cli-0.1.0.dist-info/entry_points.txt
py_mirror_cli-0.1.0.dist-info/top_level.txt
py_mirror_cli-0.1.0.dist-info/RECORD
