Metadata-Version: 2.4
Name: py-mirror-cli
Version: 0.1.0
Summary: Python pip 镜像源管理工具，类似 nrm
Author-email: Jonelee <jonelee@example.com>
Project-URL: Homepage, https://github.com/yourusername/py-mirror-cli
Project-URL: Repository, https://github.com/yourusername/py-mirror-cli
Keywords: pip,pypi,mirror,registry,manager
Classifier: Development Status :: 4 - Beta
Classifier: Intended Audience :: Developers
Classifier: License :: OSI Approved :: MIT License
Classifier: Programming Language :: Python :: 3
Classifier: Programming Language :: Python :: 3.8
Classifier: Programming Language :: Python :: 3.9
Classifier: Programming Language :: Python :: 3.10
Classifier: Programming Language :: Python :: 3.11
Classifier: Programming Language :: Python :: 3.12
Requires-Python: >=3.8
License-File: LICENSE
Requires-Dist: typer[all]>=0.9.0
Requires-Dist: rich>=13.0.0
Requires-Dist: textual>=0.47.0
Requires-Dist: requests>=2.31.0
Requires-Dist: configparser>=6.0.0
Provides-Extra: dev
Requires-Dist: pytest>=7.4.0; extra == "dev"
Requires-Dist: pytest-cov>=4.1.0; extra == "dev"
Requires-Dist: black>=23.0.0; extra == "dev"
Requires-Dist: isort>=5.12.0; extra == "dev"
Requires-Dist: flake8>=6.0.0; extra == "dev"
Dynamic: license-file
